ppg/__init__.py
ppg/agent.py
ppg/aux_training.py
ppg/critic_training.py
ppg/gae.py
ppg/networks.py
ppg/ppo_training.py
ppg/trajectory.py
ppg/test/__init__.py
ppg/test/test_gae.py
pretrain/__init__.py
pretrain/contrastive_learning.py
pretrain/contrastive_training.py
pretrain/data_augmentation.py
pretrain/environment.py
pretrain/reward.py
pretrain/state_data.py
unsupervised_on_policy/__init__.py
unsupervised_on_policy/rollout.py
unsupervised_on_policy/run_train.py
unsupervised_on_policy/ppg/__init__.py
unsupervised_on_policy/ppg/agent.py
unsupervised_on_policy/ppg/aux_training.py
unsupervised_on_policy/ppg/critic_training.py
unsupervised_on_policy/ppg/gae.py
unsupervised_on_policy/ppg/networks.py
unsupervised_on_policy/ppg/ppo_training.py
unsupervised_on_policy/ppg/trajectory.py
unsupervised_on_policy/ppg/test/__init__.py
unsupervised_on_policy/ppg/test/test_gae.py
unsupervised_on_policy/pretrain/__init__.py
unsupervised_on_policy/pretrain/contrastive_learning.py
unsupervised_on_policy/pretrain/contrastive_training.py
unsupervised_on_policy/pretrain/data_augmentation.py
unsupervised_on_policy/pretrain/environment.py
unsupervised_on_policy/pretrain/reward.py
unsupervised_on_policy/pretrain/state_data.py
unsupervised_on_policy/utils/__init__.py
unsupervised_on_policy/utils/logger.py
unsupervised_on_policy/utils/network_utils.py
unsupervised_on_policy/utils/rollout_utils.py
utils/__init__.py
utils/logger.py
utils/network_utils.py
utils/rollout_utils.py
active_pre_train_ppg-0.0.8.dist-info/LICENSE
active_pre_train_ppg-0.0.8.dist-info/METADATA
active_pre_train_ppg-0.0.8.dist-info/WHEEL
active_pre_train_ppg-0.0.8.dist-info/top_level.txt
active_pre_train_ppg-0.0.8.dist-info/RECORD
